tiny_migrations/__init__.py
tiny_migrations/__main__.py
tiny_migrations/migration_base.py
tiny_migrations/tiny_migrations.py
tiny_migrations/utils.py
tiny_migrations-0.1.2.dist-info/licenses/LICENSE
tiny_migrations-0.1.2.dist-info/METADATA
tiny_migrations-0.1.2.dist-info/WHEEL
tiny_migrations-0.1.2.dist-info/top_level.txt
tiny_migrations-0.1.2.dist-info/RECORD
