Metadata-Version: 2.4
Name: tiny-migrations
Version: 0.1.2
Summary: A tiny, lightweight, package for managing database migrations. Designed to work without INI files or dynamic module loading, making it ideal for compiled or frozen applications as well as traditional servers.
Author-email: Jonathan Few <jffreelancing@gmail.com>
Maintainer-email: Jonathan Few <jffreelancing@gmail.com>
License: MIT
Project-URL: bugs, https://github.com/ackhia/tiny_migrations/issues
Project-URL: changelog, https://github.com/ackhia/tiny_migrations/blob/master/changelog.md
Project-URL: homepage, https://github.com/ackhia/tiny_migrations
Requires-Python: >=3.10
License-File: LICENSE
Provides-Extra: test
Requires-Dist: coverage; extra == "test"
Requires-Dist: pytest; extra == "test"
Requires-Dist: ruff; extra == "test"
Requires-Dist: ty; extra == "test"
Requires-Dist: ipdb; extra == "test"
Dynamic: license-file
